nti/__init__.py
nti/ntiids/__init__.py
nti/ntiids/_compat.py
nti/ntiids/common.py
nti/ntiids/configure.zcml
nti/ntiids/interfaces.py
nti/ntiids/ntiids.py
nti/ntiids/oids.py
nti/ntiids/schema.py
nti/ntiids/tests/__init__.py
nti/ntiids/tests/test_common.py
nti/ntiids/tests/test_compat.py
nti/ntiids/tests/test_interfaces.py
nti/ntiids/tests/test_ntiids.py
nti/ntiids/tests/test_oids.py
nti/ntiids/tests/test_schema.py
nti.ntiids-1.0.0.dist-info/LICENSE
nti.ntiids-1.0.0.dist-info/METADATA
nti.ntiids-1.0.0.dist-info/WHEEL
nti.ntiids-1.0.0.dist-info/top_level.txt
nti.ntiids-1.0.0.dist-info/zip-safe
nti.ntiids-1.0.0.dist-info/RECORD
